odoo8_addon_account_compute_tax_amount-8.0.1.0.0.99.dev6-py2.7-nspkg.pth
odoo8_addon_account_compute_tax_amount-8.0.1.0.0.99.dev6.dist-info/DESCRIPTION.rst
odoo8_addon_account_compute_tax_amount-8.0.1.0.0.99.dev6.dist-info/METADATA
odoo8_addon_account_compute_tax_amount-8.0.1.0.0.99.dev6.dist-info/RECORD
odoo8_addon_account_compute_tax_amount-8.0.1.0.0.99.dev6.dist-info/WHEEL
odoo8_addon_account_compute_tax_amount-8.0.1.0.0.99.dev6.dist-info/metadata.json
odoo8_addon_account_compute_tax_amount-8.0.1.0.0.99.dev6.dist-info/namespace_packages.txt
odoo8_addon_account_compute_tax_amount-8.0.1.0.0.99.dev6.dist-info/top_level.txt
odoo_addons/account_compute_tax_amount/README.rst
odoo_addons/account_compute_tax_amount/__init__.py
odoo_addons/account_compute_tax_amount/__openerp__.py
odoo_addons/account_compute_tax_amount/account_move_line.py
odoo_addons/account_compute_tax_amount/i18n/account_compute_tax_amount.pot
odoo_addons/account_compute_tax_amount/i18n/ar.po
odoo_addons/account_compute_tax_amount/i18n/bs.po
odoo_addons/account_compute_tax_amount/i18n/cs.po
odoo_addons/account_compute_tax_amount/i18n/de.po
odoo_addons/account_compute_tax_amount/i18n/en_GB.po
odoo_addons/account_compute_tax_amount/i18n/es.po
odoo_addons/account_compute_tax_amount/i18n/es_CR.po
odoo_addons/account_compute_tax_amount/i18n/es_EC.po
odoo_addons/account_compute_tax_amount/i18n/es_MX.po
odoo_addons/account_compute_tax_amount/i18n/fr.po
odoo_addons/account_compute_tax_amount/i18n/hr.po
odoo_addons/account_compute_tax_amount/i18n/hu.po
odoo_addons/account_compute_tax_amount/i18n/id.po
odoo_addons/account_compute_tax_amount/i18n/it.po
odoo_addons/account_compute_tax_amount/i18n/ja.po
odoo_addons/account_compute_tax_amount/i18n/lt.po
odoo_addons/account_compute_tax_amount/i18n/mk.po
odoo_addons/account_compute_tax_amount/i18n/mn.po
odoo_addons/account_compute_tax_amount/i18n/nb.po
odoo_addons/account_compute_tax_amount/i18n/nl.po
odoo_addons/account_compute_tax_amount/i18n/nl_BE.po
odoo_addons/account_compute_tax_amount/i18n/pt.po
odoo_addons/account_compute_tax_amount/i18n/pt_BR.po
odoo_addons/account_compute_tax_amount/i18n/pt_PT.po
odoo_addons/account_compute_tax_amount/i18n/ro.po
odoo_addons/account_compute_tax_amount/i18n/ro_RO.po
odoo_addons/account_compute_tax_amount/i18n/ru.po
odoo_addons/account_compute_tax_amount/i18n/sl.po
odoo_addons/account_compute_tax_amount/i18n/sv.po
odoo_addons/account_compute_tax_amount/i18n/tr.po
odoo_addons/account_compute_tax_amount/i18n/zh_CN.po
